bard/__init__.py
bard/bard.py
bard/constants.py
bard/enums.py
bard/exceptions.py
bard/utils.py
bard_py-0.4.0.dist-info/LICENSE
bard_py-0.4.0.dist-info/METADATA
bard_py-0.4.0.dist-info/WHEEL
bard_py-0.4.0.dist-info/RECORD
