Metadata-Version: 2.1
Name: bard-py
Version: 0.4.0
Summary: Python Client for Bard.
License: MIT
Author: vsakkas
Author-email: vasileios.sakkas96@gmail.com
Requires-Python: >=3.10,<4.0
Classifier: License :: OSI Approved :: MIT License
Classifier: Programming Language :: Python :: 3
Classifier: Programming Language :: Python :: 3.10
Classifier: Programming Language :: Python :: 3.11
Classifier: Programming Language :: Python :: 3.12
Requires-Dist: aiohttp (>=3.8.6,<4.0.0)
